{
  "main": {
    "id": "290a66c095d0d677",
    "type": "split",
    "children": [
      {
        "id": "aac2c6f0ea9eb3a6",
        "type": "tabs",
        "children": [
          {
            "id": "df742d75ab8ea163",
            "type": "leaf",
            "state": {
              "type": "canvas",
              "state": {
                "file": "Study.canvas",
                "viewState": {
                  "x": 6186.692221817725,
                  "y": 10041.160887929218,
                  "zoom": -2.7916374482816018
                }
              },
              "icon": "lucide-layout-dashboard",
              "title": "Study"
            }
          }
        ]
      }
    ],
    "direction": "vertical"
  },
  "left": {
    "id": "8f0ccdb2bda91d97",
    "type": "split",
    "children": [
      {
        "id": "8b8fff4dfd0a3fb8",
        "type": "tabs",
        "children": [
          {
            "id": "9cca19a3b451d1a1",
            "type": "leaf",
            "state": {
              "type": "file-explorer",
              "state": {
                "sortOrder": "alphabetical",
                "autoReveal": false
              },
              "icon": "lucide-folder-closed",
              "title": "Files"
            }
          },
          {
            "id": "4fe915ba1d2beffb",
            "type": "leaf",
            "state": {
              "type": "search",
              "state": {
                "query": "tag:#Обработка",
                "matchingCase": false,
                "explainSearch": false,
                "collapseAll": false,
                "extraContext": false,
                "sortOrder": "alphabetical"
              },
              "icon": "lucide-search",
              "title": "Search"
            }
          },
          {
            "id": "64da1f4b267abf78",
            "type": "leaf",
            "state": {
              "type": "bookmarks",
              "state": {},
              "icon": "lucide-bookmark",
              "title": "Bookmarks"
            }
          }
        ]
      }
    ],
    "direction": "horizontal",
    "width": 200
  },
  "right": {
    "id": "022269da193245bd",
    "type": "split",
    "children": [
      {
        "id": "acce289f29980a65",
        "type": "tabs",
        "children": [
          {
            "id": "9a355d2d554bf3da",
            "type": "leaf",
            "state": {
              "type": "backlink",
              "state": {
                "collapseAll": false,
                "extraContext": false,
                "sortOrder": "alphabetical",
                "showSearch": false,
                "searchQuery": "",
                "backlinkCollapsed": false,
                "unlinkedCollapsed": true
              },
              "icon": "links-coming-in",
              "title": "Backlinks"
            }
          },
          {
            "id": "37f913ec6027143d",
            "type": "leaf",
            "state": {
              "type": "outgoing-link",
              "state": {
                "linksCollapsed": false,
                "unlinkedCollapsed": true
              },
              "icon": "links-going-out",
              "title": "Outgoing links"
            }
          },
          {
            "id": "f7cb5379914369ab",
            "type": "leaf",
            "state": {
              "type": "tag",
              "state": {
                "sortOrder": "frequency",
                "useHierarchy": true
              },
              "icon": "lucide-tags",
              "title": "Tags"
            }
          },
          {
            "id": "647cf4c479fbd8e9",
            "type": "leaf",
            "state": {
              "type": "outline",
              "state": {
                "followCursor": false,
                "showSearch": false,
                "searchQuery": ""
              },
              "icon": "lucide-list",
              "title": "Outline"
            }
          },
          {
            "id": "42b90dde8a4102fa",
            "type": "leaf",
            "state": {
              "type": "advanced-tables-toolbar",
              "state": {},
              "icon": "spreadsheet",
              "title": "Advanced Tables"
            }
          },
          {
            "id": "5c588d2ae18b4e28",
            "type": "leaf",
            "state": {
              "type": "calendar",
              "state": {},
              "icon": "lucide-file",
              "title": "Plugin no longer active"
            }
          },
          {
            "id": "bc9b0b373f659467",
            "type": "leaf",
            "state": {
              "type": "git-view",
              "state": {},
              "icon": "git-pull-request",
              "title": "Source Control"
            }
          }
        ],
        "currentTab": 6
      }
    ],
    "direction": "horizontal",
    "width": 200,
    "collapsed": true
  },
  "left-ribbon": {
    "hiddenItems": {
      "switcher:Open quick switcher": false,
      "graph:Open graph view": false,
      "canvas:Create new canvas": false,
      "daily-notes:Open today's daily note": false,
      "templates:Insert template": false,
      "command-palette:Open command palette": false,
      "table-editor-obsidian:Advanced Tables Toolbar": false,
      "obsidian-git:Open Git source control": false
    }
  },
  "active": "df742d75ab8ea163",
  "lastOpenFiles": [
    "Fight/Fight.md",
    "Study.canvas",
    "3_DataEngineer/DataEngineer.md",
    "DataEngineer/Data Engineer.md",
    "3_DataEngineer/unsorting/DWH appliance.md",
    "3_DataEngineer/unsorting/Hadoop.md",
    "3_DataEngineer/Cloud/Types of Cloud Databases/NoSQL/MongoDB Atlas.md",
    "3_DataEngineer/Cloud/Types of Cloud Databases/NoSQL/DynamoDB.md",
    "3_DataEngineer/Cloud/Types of Cloud Databases/NoSQL/Cosmos DB.md",
    "3_DataEngineer/Cloud/Types of Cloud Databases/NoSQL",
    "3_DataEngineer/Cloud/Types of Cloud Databases/SQL/Google Cloud SQL.md",
    "3_DataEngineer/Cloud/Types of Cloud Databases/SQL/Azure SQL Database.md",
    "3_DataEngineer/Cloud/Types of Cloud Databases/SQL/AWS RDS.md",
    "3_DataEngineer/Cloud/Types of Cloud Databases/SQL",
    "3_DataEngineer/Cloud/Types of Cloud Databases/In-Memory/Redis.md",
    "3_DataEngineer/Cloud/Types of Cloud Databases/Data Warehouse/Cloud.md",
    "3_DataEngineer/Cloud/Types of Cloud Databases/In-Memory/Memcached.md",
    "3_DataEngineer/Cloud/Types of Cloud Databases/In-Memory/In-Memory.md",
    "3_DataEngineer/Cloud/Types of Cloud Databases/Data Warehouse/BigQuery.md",
    "3_DataEngineer/Cloud/Types of Cloud Databases/In-Memory",
    "3_DataEngineer/Cloud/Types of Cloud Databases/Data Warehouse",
    "3_DataEngineer/Cloud/Types of Cloud Databases",
    "3_DataEngineer/Cloud/Types of Cloud Databases/Data Warehouse/Snowflake.md",
    "3_DataEngineer/Cloud/Types of Cloud Databases/Data Warehouse/Redshift.md",
    "3_DataEngineer/Cloud/Types of Cloud Databases/Data Warehouse/Data Warehouses.md",
    "3_DataEngineer/Cloud",
    "2_SQL/SQL Indexes/Clustered Indexes.md",
    "99_Cache/clustered_indexes.png",
    "clustered_indexes.png",
    "2_SQL/SQL Indexes/Non-clustered Inedexes.md",
    "2_SQL/SQL Indexes",
    "99_Cache/pkeyToTable.png",
    "99_Cache/Index_pointsTo_table2.png",
    "2_SQL/SQL Indexes/SQL Indexes.md",
    "5_Books/Atomic Habits/Summary/The Surprising Power of Atomic Habits.md",
    "5_Books/Atomic Habits/Summary/The Secret to Self-Control.md",
    "5_Books/Atomic Habits/Summary/The Man Who Didn't Look Right.md",
    "5_Books/Atomic Habits/Summary/The Best Way to Start a New Habit.md",
    "Untitled 1.canvas",
    "Untitled.canvas",
    "99_Cache/Dense.png",
    "Dense.png",
    "4_AI/Python/OpenCV",
    "4_AI/Python/Tensorflow",
    "4_AI/Python",
    "99_Cache/grpc.jpeg",
    "99_Cache/graphql.png",
    "99_Cache/rest api.png",
    "99_Cache/rest_api.svg",
    "Без названия 2.canvas",
    "Без названия.canvas",
    "Без названия 1.canvas"
  ]
}